ipycolorful/__init__.py
ipycolorful/_frontend.py
ipycolorful/_version.py
ipycolorful/widget.py
ipycolorful/labextension/package.json
ipycolorful/labextension/static/480.e9f383f101e537bf9eff.js
ipycolorful/labextension/static/568.d2c98666befc223bca26.js
ipycolorful/labextension/static/739.212952ffce2e17e4bd31.js
ipycolorful/labextension/static/907.a5eccb2607a161b3d7ee.js
ipycolorful/labextension/static/remoteEntry.4d4b1a1d235fd5359cc4.js
ipycolorful/labextension/static/style.js
ipycolorful/labextension/static/third-party-licenses.json
ipycolorful/nbextension/extension.js
ipycolorful/nbextension/index.js
ipycolorful/nbextension/index.js.LICENSE.txt
ipycolorful-0.1.1.data/data/etc/jupyter/nbconfig/notebook.d/ipycolorful.json
ipycolorful-0.1.1.data/data/share/jupyter/labextensions/ipycolorful/install.json
ipycolorful-0.1.1.data/data/share/jupyter/labextensions/ipycolorful/package.json
ipycolorful-0.1.1.data/data/share/jupyter/labextensions/ipycolorful/static/480.e9f383f101e537bf9eff.js
ipycolorful-0.1.1.data/data/share/jupyter/labextensions/ipycolorful/static/568.d2c98666befc223bca26.js
ipycolorful-0.1.1.data/data/share/jupyter/labextensions/ipycolorful/static/739.212952ffce2e17e4bd31.js
ipycolorful-0.1.1.data/data/share/jupyter/labextensions/ipycolorful/static/907.a5eccb2607a161b3d7ee.js
ipycolorful-0.1.1.data/data/share/jupyter/labextensions/ipycolorful/static/remoteEntry.4d4b1a1d235fd5359cc4.js
ipycolorful-0.1.1.data/data/share/jupyter/labextensions/ipycolorful/static/style.js
ipycolorful-0.1.1.data/data/share/jupyter/labextensions/ipycolorful/static/third-party-licenses.json
ipycolorful-0.1.1.data/data/share/jupyter/nbextensions/ipycolorful/extension.js
ipycolorful-0.1.1.data/data/share/jupyter/nbextensions/ipycolorful/index.js
ipycolorful-0.1.1.data/data/share/jupyter/nbextensions/ipycolorful/index.js.LICENSE.txt
ipycolorful-0.1.1.dist-info/LICENSE
ipycolorful-0.1.1.dist-info/METADATA
ipycolorful-0.1.1.dist-info/WHEEL
ipycolorful-0.1.1.dist-info/top_level.txt
ipycolorful-0.1.1.dist-info/RECORD
