Metadata-Version: 2.1
Name: ipycolorful
Version: 0.1.1
Summary: A Jupyter widget for react-colorful.
Home-page: https://github.com/joaopalmeiro/ipycolorful
Author: João Palmeiro
Author-email: jm.palmeiro@campus.fct.unl.pt
License: MIT
Keywords: jupyter,widgets,ipython
Platform: UNKNOWN
Classifier: Framework :: Jupyter
Classifier: Intended Audience :: Developers
Classifier: Intended Audience :: Science/Research
Classifier: License :: OSI Approved :: MIT License
Classifier: Programming Language :: Python :: 3
Classifier: Programming Language :: Python :: 3 :: Only
Classifier: Programming Language :: Python :: 3.6
Classifier: Programming Language :: Python :: 3.7
Classifier: Programming Language :: Python :: 3.8
Classifier: Programming Language :: Python :: 3.9
Classifier: Programming Language :: Python :: 3.10
Requires-Python: >=3.6
License-File: LICENSE
Requires-Dist: ipywidgets (<8,>=7.0.0)
